<?xml version="1.0" encoding="utf-8" ?>
<Floating id="'popup'" name="'popup'" widthPt="100" heightPt="100"  skin:Paint-color = "0x000000" skin:Paint-alpha = "0.5"  on-resize=" 
		$this.scaleContent = $Lib.current.stage.stageWidth / 1280;">
    <ViewStack id="'floatStack'" wrap="true" widthPt="100" heightPt="100" on-display="$this.show(@content);" >
		<meta:include src="ui/popup/tipPopup.xml"/>
		<meta:include src="ui/popup/onBattle.xml"/>
		<meta:include src="ui/popup/overcomeView.xml"/>
		<meta:include src="ui/popup/failureView.xml"/>
		<meta:include src="ui/popup/resurrectionTip.xml"/>
		<meta:include src="ui/popup/gainGoods.xml"/>
    </ViewStack>
</Floating>